{
  "collectionName": "components_component_info_details",
  "info": {
    "displayName": "Info Details"
  },
  "options": {},
  "attributes": {
    "image": {
      "allowedTypes": [
        "images",
        "files",
        "videos",
        "audios"
      ],
      "type": "media",
      "multiple": false
    },
    "preHeading": {
      "type": "string"
    },
    "heading": {
      "type": "string"
    },
    "description": {
      "type": "text"
    },
    "redirectUrl": {
      "type": "text"
    }
  }
}
